momoa-0.3.0.dist-info/METADATA
momoa-0.3.0.dist-info/WHEEL
momoa/__init__.py
momoa/exceptions.py
momoa/format.py
momoa/model.py
momoa/py.typed
momoa-0.3.0.dist-info/RECORD
