Metadata-Version: 2.1
Name: momoa
Version: 0.3.0
Summary: A library for definition, validation and serialisation of Python objects based on JSONSchema specifications.
Home-page: https://momoa.readthedocs.io
Author-Email: Berislav Lopac <berislav@lopac.net>
License: MIT
Classifier: Development Status :: 4 - Beta
Classifier: License :: OSI Approved :: MIT License
Classifier: Operating System :: OS Independent
Classifier: Programming Language :: Python :: 3.8
Classifier: Programming Language :: Python :: 3.9
Classifier: Programming Language :: Python :: 3.10
Classifier: Programming Language :: Python :: 3.11
Classifier: Topic :: File Formats :: JSON :: JSON Schema
Project-URL: Homepage, https://momoa.readthedocs.io
Project-URL: Repository, https://github.com/berislavlopac/momoa
Requires-Python: >=3.9
Requires-Dist: statham-schema>=0.13.5
Requires-Dist: python-dateutil>=2.8.2
Requires-Dist: pyhumps>=3.8.0
Requires-Dist: mkapi>=1.0.14; extra == "docs"
Requires-Dist: mkdocs>=1.5.3; extra == "docs"
Requires-Dist: mkdocs-material>=9.5.17; extra == "docs"
Requires-Dist: jinja2>=3.1.3; extra == "docs"
Provides-Extra: docs
